_logging/__init__.py
_logging/logger.py
_logging/logging_config.py
_logging/timer.py
_logging/utils.py
qpboost/__init__.py
qpboost/estimator/__init__.py
qpboost/estimator/base.py
qpboost/estimator/qpboost.py
qpboost/solver/__init__.py
qpboost/solver/base.py
qpboost/solver/gurobi_solver.py
qpboost/solver/lbfgsb_solver.py
qpboost/utils/__init__.py
qpboost/utils/utils.py
qpboost-0.0.1.dist-info/LICENSE
qpboost-0.0.1.dist-info/METADATA
qpboost-0.0.1.dist-info/WHEEL
qpboost-0.0.1.dist-info/top_level.txt
qpboost-0.0.1.dist-info/RECORD
