Metadata-Version: 2.1
Name: qpboost
Version: 0.0.1
Summary: A Python package for Quadratic Programming Boosting algorithms
Home-page: https://github.com/sibirbil/QPBoost
Author: Ilker Birbil
Author-email: Ilker Birbil <sibirbil@gmail.com>
License: GNU GENERAL PUBLIC LICENSE
Project-URL: Homepage, https://github.com/sibirbil/QPBoost
Classifier: Programming Language :: Python
Classifier: Programming Language :: Python :: 3
Classifier: License :: OSI Approved :: MIT License
Classifier: Operating System :: OS Independent
Requires-Python: >=3.6
License-File: LICENSE
